{
    "id": 12430558200101,
    "customer_id": 9319172309285,
    "first_name": "Sarvesh",
    "last_name": "Nalawade",
    "company": "Svasti",
    "address1": "My Home Punawale Kate Wasti Road Kate Wasti Punawale",
    "address2": "1221",
    "city": "Pimpri-Chinchwad",
    "province": "Maharashtra",
    "country": "India",
    "zip": "411033",
    "phone": "+918805060804",
    "name": "Sarvesh Nalawade",
    "province_code": "MH",
    "country_code": "IN",
    "country_name": "India",
    "default": true
}